Metadata-Version: 2.2
Name: faiss-gpu-cu12
Version: 1.13.2
Summary: A library for efficient similarity search and clustering of dense vectors.
Keywords: search nearest neighbors
Author-Email: Di-Is <rhoxbox@gmail.com>
License: MIT License
Classifier: Development Status :: 5 - Production/Stable
Classifier: License :: OSI Approved :: MIT License
Classifier: Operating System :: POSIX
Classifier: Intended Audience :: Developers
Classifier: Intended Audience :: Science/Research
Classifier: Topic :: Scientific/Engineering :: Artificial Intelligence
Classifier: Programming Language :: Python
Classifier: Programming Language :: Python :: 3
Classifier: Programming Language :: Python :: 3.10
Classifier: Programming Language :: Python :: 3.11
Classifier: Programming Language :: Python :: 3.12
Classifier: Programming Language :: Python :: 3.13
Classifier: Programming Language :: Python :: 3 :: Only
Classifier: Environment :: GPU :: NVIDIA CUDA
Classifier: Environment :: GPU :: NVIDIA CUDA :: 12
Project-URL: faiss-gpu-wheels, https://github.com/Di-Is/faiss-gpu-wheels
Requires-Python: <3.14,>=3.10
Requires-Dist: numpy<3,>=2
Requires-Dist: packaging
Requires-Dist: nvidia-cuda-runtime-cu12>=12.1.105
Requires-Dist: nvidia-cublas-cu12>=12.1.3.1
Provides-Extra: fix-cuda
Requires-Dist: nvidia-cuda-runtime-cu12==12.1.105; extra == "fix-cuda"
Requires-Dist: nvidia-cublas-cu12==12.1.3.1; extra == "fix-cuda"
